github_backup_supabase/__init__.py
github_backup_supabase/cli.py
github_backup_supabase-1.0.4.dist-info/METADATA
github_backup_supabase-1.0.4.dist-info/WHEEL
github_backup_supabase-1.0.4.dist-info/entry_points.txt
github_backup_supabase-1.0.4.dist-info/top_level.txt
github_backup_supabase-1.0.4.dist-info/RECORD
