Metadata-Version: 2.4
Name: github-backup-supabase
Version: 1.0.4
Summary: A CLI tool to back up your GitHub repositories and upload to Supabase storage.
Home-page: https://github.com/itspsychocoder/github-backup-supabase
Author: Hussnain Ahmad
Requires-Dist: click
Requires-Dist: requests
Requires-Dist: supabase
Requires-Dist: python-dotenv
Dynamic: author
Dynamic: description
Dynamic: description-content-type
Dynamic: home-page
Dynamic: requires-dist
Dynamic: summary
